{
  "variants": {
    "": [
      {
      "model": "unclesmod:block/slate_brick", "weight": 50
      },
      {
        "model": "unclesmod:block/slate_brick_1", "weight": 100
      },
      {
        "model": "unclesmod:block/slate_brick_2", "weight": 100
      },
      {
        "model": "unclesmod:block/slate_brick_3", "weight": 100
      },
      {
        "model": "unclesmod:block/slate_brick_4", "weight": 100
      },
      {
        "model": "unclesmod:block/slate_brick_5", "weight": 100
      }
    ]
  }
}